pykap/__init__.py
pykap/client.py
pykap/exceptions.py
pykap/models.py
pykapfinance-0.1.1.dist-info/licenses/LICENSE
pykapfinance-0.1.1.dist-info/METADATA
pykapfinance-0.1.1.dist-info/WHEEL
pykapfinance-0.1.1.dist-info/top_level.txt
pykapfinance-0.1.1.dist-info/RECORD
