Metadata-Version: 2.4
Name: pykapfinance
Version: 0.1.1
Summary: Python client library for KAP (Kamuyu Aydınlatma Platformu) API
Home-page: https://github.com/cagrigungor/pykap
Author: Çağrı Güngör
Author-email: Çağrı Güngör <iletisim@cagrigor.com>
Project-URL: Homepage, https://github.com/cagrigungor/pykap
Project-URL: Bug Reports, https://github.com/cagrigungor/pykap/issues
Project-URL: Documentation, https://github.com/cagrigungor/pykap/blob/main/README.md
Project-URL: Source, https://github.com/cagrigungor/pykap
Classifier: Development Status :: 4 - Beta
Classifier: Intended Audience :: Developers
Classifier: Intended Audience :: Financial and Insurance Industry
Classifier: Topic :: Office/Business :: Financial
Classifier: Topic :: Software Development :: Libraries :: Python Modules
Classifier: License :: OSI Approved :: MIT License
Classifier: Programming Language :: Python :: 3
Classifier: Programming Language :: Python :: 3.7
Classifier: Programming Language :: Python :: 3.8
Classifier: Programming Language :: Python :: 3.9
Classifier: Programming Language :: Python :: 3.10
Classifier: Programming Language :: Python :: 3.11
Requires-Python: >=3.7
License-File: LICENSE
Requires-Dist: requests>=2.28.0
Dynamic: author
Dynamic: home-page
Dynamic: license-file
Dynamic: requires-python
